{
	"ColumnTypes": [
		{
			"type": "INT",
			"capitalized": "Int",
			"lowercased": "int",
			"rowArray": "ints",
			"nativeType": "int"
		},
		{
			"type": "LONG",
			"capitalized": "Long",
			"lowercased": "long",
			"rowArray": "longs",
			"nativeType": "long"
		},
		{
			"type": "FLOAT",
			"capitalized": "Float",
			"lowercased": "float",
			"rowArray": "floats",
			"nativeType": "float"
		},
		{
			"type": "DOUBLE",
			"capitalized": "Double",
			"lowercased": "double",
			"rowArray": "doubles",
			"nativeType": "double"
		},
		{
			"type": "STRING",
			"capitalized": "String",
			"lowercased": "string",
			"rowArray": "strings",
			"nativeType": "String"
		},
		{
			"type": "BOOLEAN",
			"capitalized": "Bool",
			"lowercased": "bool",
			"rowArray": "bools",
			"nativeType": "boolean",
			"accessorMethod": "getBoolFromRow"
		},
		{
			"type": "JSDATE",
			"capitalized": "JsDate",
			"lowercased": "jsdate",
			"rowArray": "jsdates",
			"nativeType": "long",
			"accessorMethod": "getJsDateFromRow"
		}
	]
}

